starlette_werkzeug_debugger/__init__.py
starlette_werkzeug_debugger-0.2.0.dist-info/LICENSE
starlette_werkzeug_debugger-0.2.0.dist-info/METADATA
starlette_werkzeug_debugger-0.2.0.dist-info/WHEEL
starlette_werkzeug_debugger-0.2.0.dist-info/top_level.txt
starlette_werkzeug_debugger-0.2.0.dist-info/RECORD
