Metadata-Version: 2.1
Name: starlette-werkzeug-debugger
Version: 0.2.0
Summary: Werkzeug debugger middleware for Starlette
Author-email: Miroslav Bendík <miroslav.bendik@gmail.com>
License: MIT
Project-URL: homepage, https://github.com/mireq/starlette-werkzeug-debugger
Project-URL: documentation, https://github.com/mireq/starlette-werkzeug-debugger
Project-URL: repository, https://github.com/mireq/starlette-werkzeug-debugger
Project-URL: changelog, https://github.com/mireq/starlette-werkzeug-debugger/blob/master/CHANGELOG.md
Keywords: starlette,debugger,middleware,werkzeug
Classifier: Programming Language :: Python :: 3
Requires-Python: >=3.10
License-File: LICENSE
Provides-Extra: dev
Requires-Dist: tox ; extra == 'dev'
Requires-Dist: pylint ; extra == 'dev'
Requires-Dist: pre-commit ; extra == 'dev'
Requires-Dist: bump2version ; extra == 'dev'
Requires-Dist: commitizen ; extra == 'dev'
Requires-Dist: werkzeug ; extra == 'dev'
Requires-Dist: starlette ; extra == 'dev'
